alligater/README.md
alligater/__init__.py
alligater/arm.py
alligater/cache.py
alligater/common.py
alligater/events.py
alligater/feature.py
alligater/log.py
alligater/parse.py
alligater/population.py
alligater/rand.py
alligater/rollout.py
alligater/test_common.py
alligater/test_feature.py
alligater/test_gater.py
alligater/test_log.py
alligater/test_parse.py
alligater/value.py
alligater/variant.py
crocodsl/README.md
crocodsl/__init__.py
crocodsl/common.py
crocodsl/expr.py
crocodsl/field.py
crocodsl/func.py
crocodsl/test_expr.py
crocodsl/test_field.py
crocodsl/test_func.py
crocodsl/gram/Gram.g4
crocodsl/gram/Gram.interp
crocodsl/gram/Gram.tokens
crocodsl/gram/GramLexer.interp
crocodsl/gram/GramLexer.py
crocodsl/gram/GramLexer.tokens
crocodsl/gram/GramListener.py
crocodsl/gram/GramParser.py
crocodsl/gram/gen.sh
alligater-0.5.0.dist-info/METADATA
alligater-0.5.0.dist-info/WHEEL
alligater-0.5.0.dist-info/RECORD
