Metadata-Version: 2.4
Name: alligater
Version: 0.5.0
Summary: Randomization and gating library for Python.
Author-email: Joe Nudell <jnudell@hks.harvard.edu>
License-Expression: MIT
Requires-Python: <4,>=3.11
Requires-Dist: antlr4-python3-runtime==4.13.2
Requires-Dist: mmh3~=4.1
Requires-Dist: pyyaml~=6.0
Requires-Dist: requests~=2.32
Requires-Dist: signed-id>=0.1.0
Requires-Dist: urllib3~=2.2
